checkers/__init__.py
checkers/board.py
checkers/game.py
checkers/move.py
checkers/ai/__init__.py
checkers/ai/random_ai.py
english_checkers-0.0.2.dist-info/LICENSE.txt
english_checkers-0.0.2.dist-info/METADATA
english_checkers-0.0.2.dist-info/WHEEL
english_checkers-0.0.2.dist-info/top_level.txt
english_checkers-0.0.2.dist-info/RECORD
