Metadata-Version: 2.1
Name: english-checkers
Version: 0.0.2
Summary: The English chekers game simulation package
Author: Rodion Iudenko
Author-email: rodionyudenko@gmail.com
Maintainer-email: Rodion Iudenko <rodionyudenko@gmail.com>
License: MIT License
Project-URL: homepage, http://github.com/yud-warrior/checkers
Project-URL: documentation, http://github.com/yud-warrior/checkers
Project-URL: repository, http://github.com/yud-warrior/checkers.git
Classifier: Development Status :: 2 - Pre-Alpha
Classifier: Intended Audience :: Developers
Classifier: License :: OSI Approved :: MIT License
Classifier: Programming Language :: Python :: 3
Classifier: Programming Language :: Python :: 3.10
Classifier: Programming Language :: Python :: 3.11
Classifier: Programming Language :: Python :: 3 :: Only
Requires-Python: >=3.10
License-File: LICENSE.txt
Provides-Extra: dev
Requires-Dist: pytest (==7.2.0) ; extra == 'dev'
Requires-Dist: flake8 (==6.0.0) ; extra == 'dev'
Requires-Dist: pdoc3 (==0.10.0) ; extra == 'dev'
